chesscomwrapper/__init__.py
chesscomwrapper/version.py
chesscomwrapper/src/__init__.py
chesscomwrapper/src/apimanager.py
chesscomwrapper/src/chessclub.py
chesscomwrapper/src/chesscountry.py
chesscomwrapper/src/chessleaderboards.py
chesscomwrapper/src/chessplayer.py
chesscomwrapper/src/chessstreamer.py
chesscomwrapper/src/chessteammatch.py
chesscomwrapper/src/chesstournament.py
chesscomwrapper/src/chesswrapper.py
chesscomwrapper/src/dailypuzzle.py
chesscomwrapper/src/playerarchive.py
chesscomwrapper/src/teammatchboard.py
chesscomwrapper/src/tournamentround.py
chesscomwrapper/src/tournamentroundgroup.py
chesscomwrapper/src/handlers/__init__.py
chesscomwrapper/src/handlers/chesscomhandler.py
chesscomwrapper/src/handlers/errorhandler.py
chesscomwrapper/src/handlers/requesthandler.py
chesscomwrapper/src/handlers/chesscomhandlers/__init__.py
chesscomwrapper/src/handlers/chesscomhandlers/archivehandler.py
chesscomwrapper/src/handlers/chesscomhandlers/clubhandler.py
chesscomwrapper/src/handlers/chesscomhandlers/countryhandler.py
chesscomwrapper/src/handlers/chesscomhandlers/dailypuzzlehandler.py
chesscomwrapper/src/handlers/chesscomhandlers/leaderboardshandler.py
chesscomwrapper/src/handlers/chesscomhandlers/playerhandler.py
chesscomwrapper/src/handlers/chesscomhandlers/roundhandler.py
chesscomwrapper/src/handlers/chesscomhandlers/roundinfohandler.py
chesscomwrapper/src/handlers/chesscomhandlers/streamerhandler.py
chesscomwrapper/src/handlers/chesscomhandlers/teammatchboardhandler.py
chesscomwrapper/src/handlers/chesscomhandlers/teammatchhandler.py
chesscomwrapper/src/handlers/chesscomhandlers/tournamenthandler.py
chesscomwrapper/src/handlers/errorhandlers/__init__.py
chesscomwrapper/src/handlers/errorhandlers/noneerrorhandler.py
chesscomwrapper/src/handlers/errorhandlers/raisererrorhandler.py
chesscomwrapper/src/handlers/requesthandlers/__init__.py
chesscomwrapper/src/handlers/requesthandlers/singletonrequesthandler.py
chesscomwrapper/src/models/__init__.py
chesscomwrapper-0.0.12.dist-info/LICENSE.txt
chesscomwrapper-0.0.12.dist-info/METADATA
chesscomwrapper-0.0.12.dist-info/WHEEL
chesscomwrapper-0.0.12.dist-info/top_level.txt
chesscomwrapper-0.0.12.dist-info/RECORD
