Metadata-Version: 2.1
Name: chesscomwrapper
Version: 0.0.12
Summary: A wrapper for the chess.com API
Home-page: https://github.com/nicpanozzo/chesscom-api-wrapper
Author: Nicola Panozzo
Author-email: nicolapanoz@gmail.com
License: MIT
Classifier: License :: OSI Approved :: MIT License
Classifier: Programming Language :: Python :: 3
Requires-Python: >=3.6
License-File: LICENSE.txt
Requires-Dist: requests
Provides-Extra: dev
Requires-Dist: pytest (>=3.7) ; extra == 'dev'
Requires-Dist: twine (>=1.11.0) ; extra == 'dev'
